setup.py
tamil_stopwords/__init__.py
tamil_stopwords/do.py
tamil_stopwords/stopwords.py
tamil_stopwords/tamil_stopwords_cleaned.txt
tamil_stopwords.egg-info/PKG-INFO
tamil_stopwords.egg-info/SOURCES.txt
tamil_stopwords.egg-info/dependency_links.txt
tamil_stopwords.egg-info/top_level.txt