Metadata-Version: 2.2
Name: tamil_stopwords
Version: 0.1
Summary: A simple Tamil stopwords list for NLP preprocessing
Author: Paithra Harini Sivakumar
Author-email: pavitra040604@gmail.com
Dynamic: author
Dynamic: author-email
Dynamic: summary
